pyshell/__init__.py
pyshell/ast_nodes.py
pyshell/builtins.py
pyshell/exceptions.py
pyshell/executor.py
pyshell/expansions.py
pyshell/parser.py
pyshell/state.py
pyshell/tokenizer.py
pyshell/utils.py
pyshell_terminal-1.1.2.dist-info/licenses/LICENSE
pyshell_terminal-1.1.2.dist-info/METADATA
pyshell_terminal-1.1.2.dist-info/WHEEL
pyshell_terminal-1.1.2.dist-info/entry_points.txt
pyshell_terminal-1.1.2.dist-info/top_level.txt
pyshell_terminal-1.1.2.dist-info/RECORD
