Metadata-Version: 2.4
Name: pyshell-terminal
Version: 1.1.2
Summary: A feature-rich, POSIX-compatible shell implemented in Python with advanced scripting capabilities.
Home-page: https://github.com/yogvidwankhede/PyShell
Author: Yogvid Wankhede
Author-email: yogvidwankhede@gmail.com
License: MIT
Project-URL: Homepage, https://github.com/yogvidwankhede/PyShell
Project-URL: Website, https://yogvidwankhede.com
Project-URL: Github, https://github.com/yogvidwankhede
Project-URL: LinkedIN, https://www.linkedin.com/in/yogvid-wankhede-149103231
Project-URL: Documentation, https://github.com/yogvidwankhede/PyShell/wiki
Project-URL: Bug Reports, https://github.com/yogvidwankhede/PyShell/issues
Classifier: Development Status :: 4 - Beta
Classifier: Intended Audience :: Developers
Classifier: Intended Audience :: System Administrators
Classifier: Topic :: System :: Shells
Classifier: License :: OSI Approved :: MIT License
Classifier: Programming Language :: Python :: 3.7
Classifier: Programming Language :: Python :: 3.8
Classifier: Programming Language :: Python :: 3.9
Classifier: Programming Language :: Python :: 3.10
Classifier: Programming Language :: Python :: 3.11
Classifier: Operating System :: OS Independent
Classifier: Operating System :: POSIX
Classifier: Operating System :: Microsoft :: Windows
Requires-Python: >=3.7
License-File: LICENSE
Requires-Dist: readline; platform_system != "Windows"
Requires-Dist: pyreadline3; platform_system == "Windows"
Provides-Extra: dev
Requires-Dist: pytest>=7.0; extra == "dev"
Requires-Dist: pytest-cov>=3.0; extra == "dev"
Requires-Dist: black>=22.0; extra == "dev"
Requires-Dist: flake8>=4.0; extra == "dev"
Dynamic: author
Dynamic: author-email
Dynamic: classifier
Dynamic: description
Dynamic: description-content-type
Dynamic: home-page
Dynamic: license
Dynamic: license-file
Dynamic: project-url
Dynamic: provides-extra
Dynamic: requires-dist
Dynamic: requires-python
Dynamic: summary
